visor.py
visor/__init__.py
visor/restic
visor/visor.py
visor_client-0.38.0.dist-info/METADATA
visor_client-0.38.0.dist-info/WHEEL
visor_client-0.38.0.dist-info/entry_points.txt
visor_client-0.38.0.dist-info/top_level.txt
visor_client-0.38.0.dist-info/RECORD
